{
  "additionalProperties": false,
  "description": "MCTP request: world.leave",
  "type": "object",
  "required": [
    "jsonrpc",
    "id",
    "method",
    "params"
  ],
  "properties": {
    "jsonrpc": {
      "const": "2.0",
      "type": "string"
    },
    "id": {
      "description": "JSON-RPC correlation id (string or integer, never null).",
      "anyOf": [
        {
          "type": "string"
        },
        {
          "type": "integer"
        }
      ]
    },
    "method": {
      "const": "world.leave",
      "type": "string"
    },
    "params": {
      "additionalProperties": false,
      "type": "object",
      "required": [
        "sessionId"
      ],
      "properties": {
        "sessionId": {
          "description": "Opaque session token from session.create.",
          "type": "string"
        },
        "timeoutMs": {
          "type": "number"
        },
        "requestId": {
          "type": "string"
        },
        "reason": {
          "type": "string"
        }
      }
    }
  }
}
